getmyip/__init__.py
getmyip/getmyip.py
r53dns/__init__.py
r53dns/r53_dns.py
setmy53dns/__init__.py
setmy53dns/set_my_rt53_dns.py
setmy53dns-24.12.25.data/scripts/setmy53dns
setmy53dns-24.12.25.dist-info/LICENSE.txt
setmy53dns-24.12.25.dist-info/METADATA
setmy53dns-24.12.25.dist-info/WHEEL
setmy53dns-24.12.25.dist-info/top_level.txt
setmy53dns-24.12.25.dist-info/RECORD
