Metadata-Version: 2.1
Name: setmy53dns
Version: 24.12.25
Summary: Updates a hosts Route53 record for use on reboot or waken from hibernation
Home-page: https://github.com/Glocktober/setmy53dns
Author: gunville
Author-email: rk13088@yahoo.com
Project-URL: repo, https://github.com/Glocktober/setmy53dns.git
Project-URL: overview, https://github.com/Glocktober/setmy53dns/blob/master/README.md
Keywords: 'route53 cloud dns'
Classifier: Programming Language :: Python :: 3
Classifier: License :: OSI Approved :: MIT License
Classifier: Operating System :: OS Independent
Requires-Python: >=3.6
License-File: LICENSE.txt
Requires-Dist: boto3>=1.20.54
Requires-Dist: Requests>=2.26.0
